tests/__init__.py
tests/performance/__init__.py
tests/performance/models.py
tests/performance/test_performance.py
tests/unit/__init__.py
trafalgar_log/__init__.py
trafalgar_log/app/__init__.py
trafalgar_log/core/__init__.py
trafalgar_log/core/enums.py
trafalgar_log/core/logger.py
trafalgar_log/core/utils.py
trafalgar_log-1.3.1.dist-info/LICENSE
trafalgar_log-1.3.1.dist-info/METADATA
trafalgar_log-1.3.1.dist-info/WHEEL
trafalgar_log-1.3.1.dist-info/top_level.txt
trafalgar_log-1.3.1.dist-info/RECORD
