Metadata-Version: 2.1
Name: trafalgar-log
Version: 1.3.1
Summary: A log framework that prints logs as JSON.
Home-page: https://github.com/victoraugustofd/trafalgar-log
Author: victoraugustofd
License: MIT
Keywords: logs
Classifier: License :: OSI Approved :: MIT License
Classifier: Intended Audience :: Developers
Classifier: Programming Language :: Python :: 3.8
Classifier: Topic :: System :: Logging
Requires-Python: >=3.8, <4
License-File: LICENSE
Requires-Dist: semver
Requires-Dist: uplink
Requires-Dist: dynaconf
Requires-Dist: python-json-logger
